{
    "chats": {
        "2": {
            "371106526": 68,
            "519261660": 5
        },
        "3": {
            "592115373": 9,
            "371106526": 2,
            "289337356": 98,
            "386735725": 16,
            "418275433": 52,
            "662225578": 2,
            "550450373": 25,
            "549096137": 17,
            "457562432": 62,
            "637054042": 11,
            "233164597": 21,
            "288439218": 63,
            "447381566": 8,
            "509473024": 47,
            "426271948": 11,
            "489632002": 11,
            "610663465": 16,
            "593127001": 98,
            "553338216": 7
        },
        "5": {
            "550450373": 13,
            "401438646": 2,
            "342057212": 1
        },
        "7": {
            "452768986": 26
        },
        "8": {
            "509473024": 1
        }
    }
}